{
  "development": {
    "username": "root",
    "password": null,
    "database": "acmedb",
    "host": "127.0.0.1",
    "dialect": "mysql",
    "operatorsAliases": false,
    "jwt_secret":"qweqweqw"
  },
  "test": {
    "username": "root",
    "password": null,
    "database": "acmedb",
    "host": "127.0.0.1",
    "dialect": "mysql",
    "operatorsAliases": false,
    "jwt_secret":"qweqweqw"
  },
  "production": {
    "username": "root",
    "password": null,
    "database": "acmedb",
    "host": "127.0.0.1",
    "dialect": "mysql",
    "operatorsAliases": false,
    "jwt_secret":"qweqweqw"
  }
}
